pylebanon/__init__.py
pylebanon/_version.py
pylebanon/lebanon.py
pylebanon/data/lebanon.json
pylebanon-0.1.7.dist-info/licenses/LICENSE
pylebanon-0.1.7.dist-info/METADATA
pylebanon-0.1.7.dist-info/WHEEL
pylebanon-0.1.7.dist-info/top_level.txt
pylebanon-0.1.7.dist-info/RECORD
