Metadata-Version: 2.4
Name: pylebanon
Version: 0.1.7
Summary: A Python package for Lebanon.
Author-email: Mohammad El Sakka <mohammad.el-sakka@outlook.com>
License: MIT License
Project-URL: GitHub, https://github.com/MohammadElSakka/
Project-URL: LinkedIn, https://www.linkedin.com/in/mohammad-el-sakka/
Keywords: lebanon,python
Requires-Python: >=3.10
License-File: LICENSE
Dynamic: license-file
